RunToolkit/__init__.py
RunToolkit/for_arr.py
RunToolkit/for_dict.py
RunToolkit/utils.py
RunToolkit/for_db/__init__.py
RunToolkit/for_df/__init__.py
RunToolkit/for_df/transform.py
RunToolkit/for_file/__init__.py
RunToolkit/for_file/for_excel.py
RunToolkit/for_list/__init__.py
RunToolkit/for_list/interval.py
RunToolkit/for_math/__init__.py
RunToolkit/for_math/cipher.py
RunToolkit/for_math/numbers.py
RunToolkit/for_math/operators.py
RunToolkit/for_math/patterns.py
RunToolkit/for_str/__init__.py
RunToolkit/for_str/anagram.py
RunToolkit/for_str/palindrome.py
RunToolkit/for_str/regex.py
RunToolkit/for_str/transform.py
RunToolkit-0.0.1.dist-info/DESCRIPTION.rst
RunToolkit-0.0.1.dist-info/METADATA
RunToolkit-0.0.1.dist-info/RECORD
RunToolkit-0.0.1.dist-info/WHEEL
RunToolkit-0.0.1.dist-info/metadata.json
RunToolkit-0.0.1.dist-info/top_level.txt
