Metadata-Version: 2.0
Name: RunToolkit
Version: 0.0.1
Summary: some useful tools for python
Home-page: UNKNOWN
Author: aRun
Author-email: 
Maintainer: aRun
Maintainer-email: 
License: MIT
Platform: all
Classifier: Environment :: Web Environment
Classifier: Intended Audience :: Developers
Classifier: License :: OSI Approved :: MIT License
Classifier: Operating System :: MacOS
Classifier: Operating System :: Microsoft
Classifier: Operating System :: POSIX
Classifier: Operating System :: Unix
Classifier: Topic :: Software Development :: Libraries :: Python Modules
Classifier: Programming Language :: Python :: 3.5
Classifier: Programming Language :: Python :: 3.6
Classifier: Programming Language :: Python :: 3.7
Requires-Dist: numpy (>=1.16.3)
Requires-Dist: pandas (>=0.23.4)
Requires-Dist: pyexcelerate
